sdk_fontes_betha/Autorizacao_fontes.py
sdk_fontes_betha/Fonte_dados.py
sdk_fontes_betha/__init__.py
sdk_fontes_betha-0.1.0.dist-info/licenses/LICENSE
sdk_fontes_betha-0.1.0.dist-info/METADATA
sdk_fontes_betha-0.1.0.dist-info/WHEEL
sdk_fontes_betha-0.1.0.dist-info/top_level.txt
sdk_fontes_betha-0.1.0.dist-info/RECORD
