Metadata-Version: 2.4
Name: sdk-fontes-betha
Version: 0.1.0
Summary: SDK para consumo de fontes de dados da betha
Author-email: Fernando Favaro Bonetti <FernandoEuBonetti@gmail.com>
Maintainer-email: Fernando Favaro Bonetti <FernandoEuBonetti@gmail.com>
License-Expression: MIT
Requires-Python: >=3.7
License-File: LICENSE
Requires-Dist: requests>=2.0.0
Dynamic: license-file
